{"legislative_session": "119", "identifier": "S 3175", "title": "CIPZIP Act of 2025", "from_organization": "~{\"classification\": \"upper\"}", "classification": ["bill"], "subject": [], "abstracts": [], "other_titles": [{"note": "", "title": "Community Involvement in Zone Improvement Plans Act of 2025"}, {"note": "", "title": "A bill to establish a pilot program for ZIP Code boundary changes, and for other purposes."}], "other_identifiers": [{"identifier": "ocd-bill-us-119-s3175"}], "actions": [{"description": "Read twice and referred to the Committee on Homeland Security and Governmental Affairs.", "date": "2025-11-18T05:00:00+00:00", "organization_id": "~{\"classification\": \"upper\"}", "classification": [], "related_entities": []}, {"description": "Introduced in Senate", "date": "2025-11-18T05:00:00+00:00", "organization_id": "~{\"classification\": \"upper\"}", "classification": ["introduction"], "related_entities": []}], "sponsorships": [{"name": "Joni Ernst", "classification": "cosponsor", "entity_type": "person", "primary": false, "person_id": "~{\"name\": \"Joni Ernst\"}", "organization_id": null}, {"name": "James Lankford", "classification": "primary", "entity_type": "person", "primary": true, "person_id": "~{\"name\": \"James Lankford\"}", "organization_id": null}], "related_bills": [], "versions": [{"note": "Introduced in Senate", "links": [{"url": "https://www.govinfo.gov/content/pkg/BILLS-119s3175is/xml/BILLS-119s3175is.xml", "media_type": "text/xml"}, {"url": "https://www.govinfo.gov/content/pkg/BILLS-119s3175is/pdf/BILLS-119s3175is.pdf", "media_type": "application/pdf"}], "date": "2025-11-18", "classification": ""}], "documents": [], "citations": [], "sources": [{"url": "https://www.govinfo.gov/bulkdata/BILLSTATUS/119/s/BILLSTATUS-119s3175.xml", "note": ""}, {"url": "https://congress.gov/bill/119th-congress/senate-bill/3175", "note": ""}], "extras": {"cosponsor_bioguides": ["E000295"], "sponsor_bioguides": ["L000575"]}, "jurisdiction": {"id": "ocd-jurisdiction/country:us/government", "name": "United States", "classification": "country", "division_id": "ocd-division/country:us"}, "scraped_at": "2026-07-14T09:14:37+00:00", "_id": "7007f746-7f64-11f1-92bd-96a1326147e7"}